openapi_fal_rest/__init__.py
openapi_fal_rest/api/__init__.py
openapi_fal_rest/api/billing/__init__.py
openapi_fal_rest/api/billing/get_setup_intent_key.py
openapi_fal_rest/api/billing/get_user_details.py
openapi_fal_rest/api/billing/get_user_invoices.py
openapi_fal_rest/api/billing/get_user_payment_methods.py
openapi_fal_rest/api/billing/get_user_spending.py
openapi_fal_rest/api/billing/upcoming_invoice.py
openapi_fal_rest/api/billing/update_customer_budget.py
openapi_fal_rest/api/files/__init__.py
openapi_fal_rest/api/files/check_dir_hash.py
openapi_fal_rest/api/files/delete.py
openapi_fal_rest/api/files/download.py
openapi_fal_rest/api/files/file_exists.py
openapi_fal_rest/api/files/list_directory.py
openapi_fal_rest/api/files/list_root.py
openapi_fal_rest/api/files/upload_from_url.py
openapi_fal_rest/api/files/upload_local_file.py
openapi_fal_rest/api/keys/__init__.py
openapi_fal_rest/api/keys/create_key.py
openapi_fal_rest/api/keys/delete_key.py
openapi_fal_rest/api/keys/list_keys.py
openapi_fal_rest/api/logs/__init__.py
openapi_fal_rest/api/logs/list_since.py
openapi_fal_rest/api/usage/__init__.py
openapi_fal_rest/api/usage/get_custom_usage_per_machine.py
openapi_fal_rest/api/usage/get_shared_usage_per_app.py
openapi_fal_rest/api/usage/get_usage_records.py
openapi_fal_rest/api/usage/per_machine_usage.py
openapi_fal_rest/api/usage/per_machine_usage_details.py
openapi_fal_rest/client.py
openapi_fal_rest/errors.py
openapi_fal_rest/models/__init__.py
openapi_fal_rest/models/body_upload_local_file.py
openapi_fal_rest/models/customer_details.py
openapi_fal_rest/models/file_spec.py
openapi_fal_rest/models/grouped_usage_detail.py
openapi_fal_rest/models/hash_check.py
openapi_fal_rest/models/http_validation_error.py
openapi_fal_rest/models/invoice.py
openapi_fal_rest/models/invoice_item.py
openapi_fal_rest/models/key_scope.py
openapi_fal_rest/models/log_entry.py
openapi_fal_rest/models/new_user_key.py
openapi_fal_rest/models/payment_method.py
fal_serverless-0.6.41.dist-info/entry_points.txt
fal_serverless-0.6.41.dist-info/METADATA
fal_serverless-0.6.41.dist-info/WHEEL
fal_serverless-0.6.41.dist-info/RECORD
